Metadata-Version: 2.4
Name: typed-mexc
Version: 0.1.1
Summary: A fully typed, validated async client for the MEXC API.
Author-email: Marcel Claramunt <marcel@tribulnation.com>
Project-URL: repo, https://github.com/tribulnation/mexc.git
Requires-Python: >=3.10
Requires-Dist: lazy-loader
Requires-Dist: httpx
Requires-Dist: pydantic
Requires-Dist: protobuf==3.20
Requires-Dist: websockets
Requires-Dist: orjson
